Metadata-Version: 2.4
Name: cloudmusic-auto-player
Version: 1.0.2
Summary: 网易云音乐 MCP 控制器 - 提供全局快捷键、搜索单曲播放、搜索歌单播放、自定义歌单管理、每日推荐和私人漫游等丰富功能
Project-URL: Homepage, https://github.com/xiduan/CloudMusic_Auto_Player
Project-URL: Repository, https://github.com/xiduan/CloudMusic_Auto_Player
Project-URL: Issues, https://github.com/xiduan/CloudMusic_Auto_Player/issues
Author-email: xiande <lxd4094@foxmail.com>
License: MIT
Keywords: automation,controller,mcp,music,netease
Classifier: Development Status :: 5 - Production/Stable
Classifier: Intended Audience :: End Users/Desktop
Classifier: License :: OSI Approved :: MIT License
Classifier: Operating System :: MacOS
Classifier: Operating System :: Microsoft :: Windows
Classifier: Programming Language :: Python :: 3
Classifier: Programming Language :: Python :: 3.10
Classifier: Programming Language :: Python :: 3.11
Classifier: Programming Language :: Python :: 3.12
Classifier: Topic :: Multimedia :: Sound/Audio :: Players
Classifier: Topic :: Software Development :: Libraries :: Python Modules
Requires-Python: >=3.10
Requires-Dist: fastmcp>=2.0.0
Requires-Dist: psutil>=5.9.0
Requires-Dist: pyautogui>=0.9.54
Requires-Dist: pywin32>=306; platform_system == 'Windows'
Requires-Dist: requests>=2.28.0
Requires-Dist: selenium>=4.0.0
Provides-Extra: dev
Requires-Dist: black>=23.0.0; extra == 'dev'
Requires-Dist: flake8>=6.0.0; extra == 'dev'
Requires-Dist: isort>=5.12.0; extra == 'dev'
Requires-Dist: mypy>=1.0.0; extra == 'dev'
Requires-Dist: pytest-cov>=4.0.0; extra == 'dev'
Requires-Dist: pytest>=7.0.0; extra == 'dev'
